{
  "kind": "OBJECT",
  "name": "CarImage",
  "description": null,
  "fields": [
    {
      "name": "id",
      "description": "Image id",
      "args": [],
      "type": {
        "kind": "SCALAR",
        "name": "ID",
        "ofType": null
      },
      "isDeprecated": false,
      "deprecationReason": null
    },
    {
      "name": "url",
      "description": "Image url",
      "args": [],
      "type": {
        "kind": "SCALAR",
        "name": "String",
        "ofType": null
      },
      "isDeprecated": false,
      "deprecationReason": null
    },
    {
      "name": "width",
      "description": "Image width in pixels",
      "args": [],
      "type": {
        "kind": "SCALAR",
        "name": "Int",
        "ofType": null
      },
      "isDeprecated": false,
      "deprecationReason": null
    },
    {
      "name": "height",
      "description": "Image height in pixels",
      "args": [],
      "type": {
        "kind": "SCALAR",
        "name": "Int",
        "ofType": null
      },
      "isDeprecated": false,
      "deprecationReason": null
    },
    {
      "name": "type",
      "description": "Image type",
      "args": [],
      "type": {
        "kind": "ENUM",
        "name": "CarImageType",
        "ofType": null
      },
      "isDeprecated": false,
      "deprecationReason": null
    }
  ],
  "inputFields": null,
  "interfaces": [],
  "enumValues": null,
  "possibleTypes": null
}