{
  "kind": "OBJECT",
  "name": "OCPIEnvironmentalImpact",
  "description": "Amount of waste produced/emitted per kWh.",
  "fields": [
    {
      "name": "category",
      "description": "The environmental impact category of this value.",
      "args": [],
      "type": {
        "kind": "ENUM",
        "name": "OCPIEnvironmentalImpactCategory",
        "ofType": null
      },
      "isDeprecated": false,
      "deprecationReason": null
    },
    {
      "name": "amount",
      "description": "Amount of this portion in g/kWh.",
      "args": [],
      "type": {
        "kind": "SCALAR",
        "name": "Int",
        "ofType": null
      },
      "isDeprecated": false,
      "deprecationReason": null
    }
  ],
  "inputFields": null,
  "interfaces": [],
  "enumValues": null,
  "possibleTypes": null
}