{
  "kind": "OBJECT",
  "name": "RequestRoute",
  "description": null,
  "fields": [
    {
      "name": "amenities",
      "description": "Desired amenities near the stations, within a 1 km radius",
      "args": [],
      "type": {
        "kind": "LIST",
        "name": null,
        "ofType": {
          "kind": "SCALAR",
          "name": "String",
          "ofType": null
        }
      },
      "isDeprecated": false,
      "deprecationReason": null
    },
    {
      "name": "operatorIds",
      "description": "Requested operators",
      "args": [],
      "type": {
        "kind": "LIST",
        "name": null,
        "ofType": {
          "kind": "SCALAR",
          "name": "String",
          "ofType": null
        }
      },
      "isDeprecated": false,
      "deprecationReason": null
    },
    {
      "name": "operatorRequired",
      "description": "Preferred operators are required. In case there are no preferred operators the route cannot be calculated",
      "args": [],
      "type": {
        "kind": "SCALAR",
        "name": "Boolean",
        "ofType": null
      },
      "isDeprecated": false,
      "deprecationReason": null
    },
    {
      "name": "operatorPrefer",
      "description": "Encourage the route to use preferred operators. In case there are no preferred operators the route can still be calculated",
      "args": [],
      "type": {
        "kind": "SCALAR",
        "name": "Boolean",
        "ofType": null
      },
      "isDeprecated": false,
      "deprecationReason": null
    },
    {
      "name": "season",
      "description": "Season",
      "args": [],
      "type": {
        "kind": "ENUM",
        "name": "RouteSeason",
        "ofType": null
      },
      "isDeprecated": false,
      "deprecationReason": null
    },
    {
      "name": "safeRiskMargin",
      "description": "Percentage for the minimum limit of the battery capacity before a recharge. The value should be between 0 and 60, with a default of 10%",
      "args": [],
      "type": {
        "kind": "SCALAR",
        "name": "Int",
        "ofType": null
      },
      "isDeprecated": false,
      "deprecationReason": null
    },
    {
      "name": "origin",
      "description": "Origin of a route",
      "args": [],
      "type": {
        "kind": "OBJECT",
        "name": "FeaturePoint",
        "ofType": null
      },
      "isDeprecated": false,
      "deprecationReason": null
    },
    {
      "name": "destination",
      "description": "Destination of a route",
      "args": [],
      "type": {
        "kind": "OBJECT",
        "name": "FeaturePoint",
        "ofType": null
      },
      "isDeprecated": false,
      "deprecationReason": null
    },
    {
      "name": "via",
      "description": "Locations where a route will stop",
      "args": [],
      "type": {
        "kind": "LIST",
        "name": null,
        "ofType": {
          "kind": "OBJECT",
          "name": "FeaturePoint",
          "ofType": null
        }
      },
      "isDeprecated": false,
      "deprecationReason": null
    },
    {
      "name": "stationsAlongRouteRadius",
      "description": "Radius in meters for alternative stations along a route (min 500 - max 5000)",
      "args": [],
      "type": {
        "kind": "SCALAR",
        "name": "Int",
        "ofType": null
      },
      "isDeprecated": false,
      "deprecationReason": null
    }
  ],
  "inputFields": null,
  "interfaces": [],
  "enumValues": null,
  "possibleTypes": null
}